nebula/Images/accuracy_activated.png
nebula/Images/accuracy_deactivated.png
nebula/Images/add_bookmark.png
nebula/Images/add_image.png
nebula/Images/add_tool.png
nebula/Images/agent_off.png
nebula/Images/agent_on.png
nebula/Images/ai_note_taking_off.png
nebula/Images/ai_note_taking_on.png
nebula/Images/arrow.png
nebula/Images/autonomous_off.png
nebula/Images/autonomous_on.png
nebula/Images/blur.png
nebula/Images/bold.png
nebula/Images/bookmarks.png
nebula/Images/bullet_list.png
nebula/Images/c2.png
nebula/Images/clear.png
nebula/Images/clicked.png
nebula/Images/close_tab.png
nebula/Images/code_analysis_off.png
nebula/Images/code_analysis_on.png
nebula/Images/coins.png
nebula/Images/confidence.png
nebula/Images/crop.png
nebula/Images/dark_mode.png
nebula/Images/decoy.png
nebula/Images/decrease_font.png
nebula/Images/directory.png
nebula/Images/draw_box.png
nebula/Images/eclipse.png
nebula/Images/eclipse_on.png
nebula/Images/eco_mode_off.png
nebula/Images/eco_mode_on.png
nebula/Images/engagement.png
nebula/Images/file.png
nebula/Images/flag.png
nebula/Images/folder.png
nebula/Images/free_activated.png
nebula/Images/free_deactivated.png
nebula/Images/heading.png
nebula/Images/help.png
nebula/Images/highlight.png
nebula/Images/image_edit.png
nebula/Images/incognito_mode_off.png
nebula/Images/incognito_mode_on.png
nebula/Images/increase_font.png
nebula/Images/is_coming.png
nebula/Images/italic.png
nebula/Images/light_mode.png
nebula/Images/lightbulb-off.png
nebula/Images/lightbulb-on.png
nebula/Images/logo.JPG
nebula/Images/logo.png
nebula/Images/lowercase.png
nebula/Images/model_selection.png
nebula/Images/numbered_list.png
nebula/Images/paragraph.png
nebula/Images/pluto.png
nebula/Images/pop_out.png
nebula/Images/redo.png
nebula/Images/refresh_credits.png
nebula/Images/remove_bookmark.png
nebula/Images/resume_autonomous_mode.png
nebula/Images/save.png
nebula/Images/screenshot.png
nebula/Images/search.png
nebula/Images/search_off.png
nebula/Images/search_on.png
nebula_ai-2.0.0b17.dist-info/LICENSE.md
nebula_ai-2.0.0b17.dist-info/METADATA
nebula_ai-2.0.0b17.dist-info/WHEEL
nebula_ai-2.0.0b17.dist-info/entry_points.txt
nebula_ai-2.0.0b17.dist-info/RECORD
