Metadata-Version: 2.3
Name: nebula-ai
Version: 2.0.0b17
Summary: AI-Powered Ethical Hacking Assistant
License: BSD
Keywords: AI,ethical hacking,nmap,zap,crackmapexec
Author: David I
Author-email: david@berylliumsec.com
Requires-Python: >=3.11,<=3.13.3
Classifier: Development Status :: 4 - Beta
Classifier: Intended Audience :: Developers
Classifier: License :: OSI Approved :: BSD License
Classifier: License :: Other/Proprietary License
Classifier: Programming Language :: Python :: 3
Classifier: Programming Language :: Python :: 3.11
Classifier: Programming Language :: Python :: 3.12
Classifier: Programming Language :: Python :: 3.13
Provides-Extra: flash
Requires-Dist: Cython
Requires-Dist: Faker
Requires-Dist: IPython
Requires-Dist: PyQt6
Requires-Dist: Pygments
Requires-Dist: Whoosh
Requires-Dist: accelerate
Requires-Dist: bitsandbytes
Requires-Dist: boto3
Requires-Dist: chromadb
Requires-Dist: duckduckgo-search
Requires-Dist: fastapi
Requires-Dist: jq
Requires-Dist: langchain
Requires-Dist: langchain-community (==0.3.16)
Requires-Dist: langchain-core
Requires-Dist: langchain-experimental
Requires-Dist: langchain-huggingface
Requires-Dist: langchain_chroma
Requires-Dist: langchain_ollama
Requires-Dist: langchain_openai
Requires-Dist: numpy
Requires-Dist: ollama
Requires-Dist: opencv-python
Requires-Dist: prompt_toolkit
Requires-Dist: psutil
Requires-Dist: pydantic
Requires-Dist: qdarkstyle
Requires-Dist: regex
Requires-Dist: requests
Requires-Dist: sentence-transformers
Requires-Dist: setuptools
Requires-Dist: tiktoken
Requires-Dist: toml
Requires-Dist: torch
Requires-Dist: transformers
Requires-Dist: typing-extensions
Requires-Dist: unstructured
Requires-Dist: uvicorn
Requires-Dist: websockets
Project-URL: Homepage, https://github.com/berylliumsec/nebula
